theremin/__init__.py
theremin/audio.py
theremin/audio_features.py
theremin/dag_audio_features.py
theremin/display.py
theremin/main.py
theremin/pipelines.py
theremin/script_utils.py
theremin/util.py
theremin/video_features.py
theremin/examples/__init__.py
theremin/examples/keyboard_synth.py
theremin/examples/multimodal.py
theremin/examples/video_theremin.py
theremin/framework/__init__.py
theremin/framework/base.py
theremin/framework/storage.py
theremin/framework/testing.py
theremin-0.0.7.dist-info/licenses/LICENSE
theremin-0.0.7.dist-info/METADATA
theremin-0.0.7.dist-info/WHEEL
theremin-0.0.7.dist-info/entry_points.txt
theremin-0.0.7.dist-info/top_level.txt
theremin-0.0.7.dist-info/RECORD
