Metadata-Version: 2.4
Name: theremin
Version: 0.0.7
Summary: A video-to-sound theremin
Home-page: https://github.com/thorwhalen/theremin
Author: Thor Whalen
License: mit
Platform: any
License-File: LICENSE
Requires-Dist: dol
Requires-Dist: i2
Requires-Dist: cw
Requires-Dist: meshed
Requires-Dist: opencv-python
Requires-Dist: hum
Requires-Dist: mediapipe
Provides-Extra: testing
Dynamic: license-file
